eurelis_llmatoolkit/__init__.py
eurelis_llmatoolkit/llamaindex/abstract_wrapper.py
eurelis_llmatoolkit/llamaindex/chatbot_wrapper.py
eurelis_llmatoolkit/llamaindex/config_loader.py
eurelis_llmatoolkit/llamaindex/console.py
eurelis_llmatoolkit/llamaindex/ingestion_wrapper.py
eurelis_llmatoolkit/llamaindex/react_wrapper.py
eurelis_llmatoolkit/llamaindex/search_wrapper.py
eurelis_llmatoolkit/llamaindex/callbacks/error_logging.py
eurelis_llmatoolkit/llamaindex/chat_memory_persistence/abstract_memory_persistence_handler.py
eurelis_llmatoolkit/llamaindex/chat_memory_persistence/json_persistence_handler.py
eurelis_llmatoolkit/llamaindex/factories/__init__.py
eurelis_llmatoolkit/llamaindex/factories/cache_factory.py
eurelis_llmatoolkit/llamaindex/factories/callback_factory.py
eurelis_llmatoolkit/llamaindex/factories/chat_engine_factory.py
eurelis_llmatoolkit/llamaindex/factories/documentstore_factory.py
eurelis_llmatoolkit/llamaindex/factories/embedding_factory.py
eurelis_llmatoolkit/llamaindex/factories/llm_factory.py
eurelis_llmatoolkit/llamaindex/factories/memory_factory.py
eurelis_llmatoolkit/llamaindex/factories/memory_persistence_factory.py
eurelis_llmatoolkit/llamaindex/factories/node_postprocessor_factory.py
eurelis_llmatoolkit/llamaindex/factories/reader_factory.py
eurelis_llmatoolkit/llamaindex/factories/retriever_factory.py
eurelis_llmatoolkit/llamaindex/factories/transformation_factory.py
eurelis_llmatoolkit/llamaindex/factories/vectorstore_factory.py
eurelis_llmatoolkit/llamaindex/readers/__init__.py
eurelis_llmatoolkit/llamaindex/readers/abstract_fs_reader.py
eurelis_llmatoolkit/llamaindex/readers/abstract_reader_adapter.py
eurelis_llmatoolkit/llamaindex/readers/advanced_sitemap_reader.py
eurelis_llmatoolkit/llamaindex/readers/community_simple_webpage_reader.py
eurelis_llmatoolkit/llamaindex/readers/community_sitemap_reader.py
eurelis_llmatoolkit/llamaindex/readers/pdf_file_reader.py
eurelis_llmatoolkit/llamaindex/readers/txt_file_reader.py
eurelis_llmatoolkit-2.0.0.dist-info/METADATA
eurelis_llmatoolkit-2.0.0.dist-info/WHEEL
eurelis_llmatoolkit-2.0.0.dist-info/entry_points.txt
eurelis_llmatoolkit-2.0.0.dist-info/licenses/LICENSE
eurelis_llmatoolkit-2.0.0.dist-info/RECORD
