Metadata-Version: 2.4
Name: eurelis-llmatoolkit
Version: 2.0.0
Summary: Framework to build and manage IA based applications. Based on Langchain and LlamaIndex under the hood.
Project-URL: Homepage, https://github.com/Eurelis/Eurelis-LlmaToolkit
Project-URL: Bug Tracker, https://github.com/Eurelis/Eurelis-LlmaToolkit/issues
Author-email: Vincent LAMBERT <v.lambert@eurelis.com>, Jérôme DIAZ <j.diaz@eurelis.com>, Nicolas LOISY <n.loisy@eurelis.com>
License-File: LICENSE
Classifier: Operating System :: OS Independent
Classifier: Programming Language :: Python :: 3
Requires-Python: >=3.11.3
Requires-Dist: click==8.1.7
Requires-Dist: python-dotenv==1.0.0
Provides-Extra: anthropic
Requires-Dist: anthropic>=0.49.0; extra == 'anthropic'
Requires-Dist: llama-index-llms-anthropic>=0.6.10; extra == 'anthropic'
Provides-Extra: chroma
Requires-Dist: chromadb>=0.6.3; extra == 'chroma'
Requires-Dist: llama-index-vector-stores-chroma>=0.4.1; extra == 'chroma'
Provides-Extra: huggingface
Requires-Dist: llama-index-embeddings-huggingface>=0.5.2; extra == 'huggingface'
Requires-Dist: sentence-transformers>=3.4.1; extra == 'huggingface'
Provides-Extra: llamaindex
Requires-Dist: llama-index-readers-web>=0.3.8; extra == 'llamaindex'
Requires-Dist: llama-index==0.13.3; extra == 'llamaindex'
Provides-Extra: markdown
Requires-Dist: markdown>=3.7; extra == 'markdown'
Provides-Extra: mongodb
Requires-Dist: llama-index-storage-docstore-mongodb>=0.3.0; extra == 'mongodb'
Requires-Dist: llama-index-vector-stores-mongodb>=0.5.0; extra == 'mongodb'
Requires-Dist: motor>=3.7.0; extra == 'mongodb'
Requires-Dist: pymongo<4.10; extra == 'mongodb'
Provides-Extra: openai
Requires-Dist: llama-index-llms-openai>=0.5.4; extra == 'openai'
Provides-Extra: pdf
Requires-Dist: pymupdf4llm>=0.0.17; extra == 'pdf'
Requires-Dist: pymupdf>=1.25.4; extra == 'pdf'
Provides-Extra: sentry
Requires-Dist: sentry-sdk>=2.23.1; extra == 'sentry'
Provides-Extra: sitemap
Requires-Dist: beautifulsoup4>=4.13.3; extra == 'sitemap'
Requires-Dist: lxml>=5.3.1; extra == 'sitemap'
